nsii/__init__.py
nsii/core.py
nsii/fps.py
nsii/image.py
nsii/io.py
nsii/master.py
nsii/terminal.py
nsii/tools.py
nsii-0.0.1.dist-info/METADATA
nsii-0.0.1.dist-info/WHEEL
nsii-0.0.1.dist-info/licenses/license
nsii-0.0.1.dist-info/RECORD
