Metadata-Version: 2.1
Name: nsii
Version: 0.0.1
Summary: Simple CLI for python that uses only native python libraries !
Project-URL: Homepage, https://github.com/killianc3/nsii
Project-URL: Bug Tracker, https://github.com/killianc3/nsii/issues
Author-email: killianfrr <killiancharrier8@gmail.com>
License:                                  Apache License
Classifier: License :: OSI Approved :: MIT License
Classifier: Operating System :: OS Independent
Classifier: Programming Language :: Python :: 3
Requires-Python: >=3.7
